zfc/__init__.py
zfc/natural_number.py
pyZFC-0.2.0.dist-info/LICENSE
pyZFC-0.2.0.dist-info/METADATA
pyZFC-0.2.0.dist-info/WHEEL
pyZFC-0.2.0.dist-info/top_level.txt
pyZFC-0.2.0.dist-info/RECORD
