Metadata-Version: 2.1
Name: pyZFC
Version: 0.2.0
Summary: (ZFC) set-theoretic definition of natural numbers.
Author-email: Yuanhao 'Nyoeghau' Chen <nyoeghau@nyoeghau.com>
License: # MIT License        
Project-URL: Homepage, https://github.com/edward-martyr/ZFC
Project-URL: Source, https://github.com/edward-martyr/ZFC
Project-URL: Bug Tracker, https://github.com/edward-martyr/ZFC/issues
Classifier: Programming Language :: Python :: 3.10
Classifier: Programming Language :: Python :: 3.11
Classifier: Development Status :: 3 - Alpha
Classifier: Topic :: Scientific/Engineering :: Mathematics
Classifier: License :: OSI Approved :: MIT License
Classifier: Operating System :: OS Independent
Requires-Python: >=3.10
License-File: LICENSE
Provides-Extra: lint
Requires-Dist: black (==22.6.0) ; extra == 'lint'
Requires-Dist: flake8 (==4.0.1) ; extra == 'lint'
Requires-Dist: isort (==5.10.1) ; extra == 'lint'
Requires-Dist: mypy (==0.971) ; extra == 'lint'
Provides-Extra: unittest
Requires-Dist: coverage[toml] ; extra == 'unittest'
